polygon_identity/__init__.py
polygon_identity/identity.py
polygon_identity/social_recovery.py
polygon_identity/types.py
polygon_identity/utils.py
polygon_identity/zk_identity.py
polygon_identity/django/__init__.py
polygon_identity/django/auth_backend.py
polygon_identity/django/middleware.py
polygon_identity/fastapi/__init__.py
polygon_identity/fastapi/dependencies.py
polygon_identity/fastapi/router.py
polygon_identity-0.1.0.dist-info/licenses/LICENSE
tests/__init__.py
tests/test_identity.py
polygon_identity-0.1.0.dist-info/METADATA
polygon_identity-0.1.0.dist-info/WHEEL
polygon_identity-0.1.0.dist-info/top_level.txt
polygon_identity-0.1.0.dist-info/RECORD
