Metadata-Version: 2.4
Name: polygon-identity
Version: 0.1.0
Summary: Polygon-based identity management system for Python
Home-page: https://github.com/Usamatahir23/polygon_identity_py
Author: Usama Tahir
Author-email: usama.tahir.choudhary@gmail.com
Project-URL: Bug Reports, https://github.com/Usamatahir23/polygon_identity_py/issues
Project-URL: Source, https://github.com/Usamatahir23/polygon_identity_py
Project-URL: Documentation, https://github.com/Usamatahir23/polygon_identity_py#readme
Keywords: polygon blockchain identity ethereum web3 social-recovery zk-proof decentralized
Classifier: Development Status :: 3 - Alpha
Classifier: Intended Audience :: Developers
Classifier: License :: OSI Approved :: MIT License
Classifier: Operating System :: OS Independent
Classifier: Programming Language :: Python :: 3
Classifier: Programming Language :: Python :: 3.8
Classifier: Programming Language :: Python :: 3.9
Classifier: Programming Language :: Python :: 3.10
Classifier: Programming Language :: Python :: 3.11
Classifier: Programming Language :: Python :: 3.12
Requires-Python: >=3.8
License-File: LICENSE
Requires-Dist: web3>=6.0.0
Requires-Dist: cryptography>=41.0.0
Requires-Dist: PyJWT>=2.8.0
Requires-Dist: requests>=2.31.0
Requires-Dist: PyNaCl>=1.5.0
Requires-Dist: python-dotenv>=1.0.0
Provides-Extra: django
Requires-Dist: django>=4.0.0; extra == "django"
Provides-Extra: fastapi
Requires-Dist: fastapi>=0.100.0; extra == "fastapi"
Requires-Dist: uvicorn>=0.23.0; extra == "fastapi"
Provides-Extra: dev
Requires-Dist: pytest>=7.4.0; extra == "dev"
Requires-Dist: pytest-asyncio>=0.21.0; extra == "dev"
Requires-Dist: black>=23.0.0; extra == "dev"
Requires-Dist: flake8>=6.0.0; extra == "dev"
Requires-Dist: mypy>=1.5.0; extra == "dev"
Dynamic: author
Dynamic: author-email
Dynamic: classifier
Dynamic: description
Dynamic: description-content-type
Dynamic: home-page
Dynamic: keywords
Dynamic: license-file
Dynamic: project-url
Dynamic: provides-extra
Dynamic: requires-dist
Dynamic: requires-python
Dynamic: summary
